{
  "usingComponents": {
    "t-toast": "tdesign-miniprogram/toast/toast",
    "t-icon": "tdesign-miniprogram/icon/icon",
    "t-input": "tdesign-miniprogram/input/input",
    "t-button": "tdesign-miniprogram/button/button",
    "t-picker": "tdesign-miniprogram/picker/picker",
    "t-picker-item": "tdesign-miniprogram/picker-item/picker-item",
    "t-loading": "tdesign-miniprogram/loading/loading",
    "t-popup": "tdesign-miniprogram/popup/popup"
  },
  "navigationBarTitleText": "库存管理",
  "enablePullDownRefresh": true
}
